irradiance_pv/__init__.py
irradiance_pv/example.py
irradiance_pv/irradiance_pv.py
irradiance_pv/spa_sb.py
irradiance_pv-1.27.dist-info/license.txt
irradiance_pv-1.27.dist-info/WHEEL
irradiance_pv-1.27.dist-info/METADATA
irradiance_pv-1.27.dist-info/RECORD
