Metadata-Version: 2.1
Name: irradiance-pv
Version: 1.27
Summary: "Calculate in plane irradiance for a surface"
Home-page: https://github.com/sbadillo/irradiance-pv
License: MIT
Author: -sergiob
Author-email: sbadilloworks@gmail.com
Classifier: License :: OSI Approved :: MIT License
Classifier: Programming Language :: Python :: 2
Classifier: Programming Language :: Python :: 2.7
Classifier: Programming Language :: Python :: 3
Classifier: Programming Language :: Python :: 3.4
Classifier: Programming Language :: Python :: 3.5
Classifier: Programming Language :: Python :: 3.6
Classifier: Programming Language :: Python :: 3.7
Classifier: Programming Language :: Python :: 3.8
Classifier: Programming Language :: Python :: 3.9
